{"eGh4x8c/M/L35WsM4koXYg==":"jee%20jay%20cars-128x128.png","Ht8GWJqPGSyf7BdF16llmQ==":"img-20170902-wa0042-1152x864.jpg","6nkTWArpW7/YPUw1DVPoqw==":"40023509-speedometer-wallpapers-2000x1125.jpg","Q4RnGisGQgDW/jYGloEoSQ==":"img-20170902-wa0023-1280x720.jpg","j0TQBeav3LihjMpDUQ/ZXw==":"img-20170902-wa0029-800x599.jpg","iYVjz4CEDxtyTNqiW7RAfg==":"img-20170902-wa0032-800x599.jpg","Y3mPTfdiqswKygMl1OwQkQ==":"img-20170902-wa0030-800x599.jpg","yQ+HDIRmEHejjOyImpDyww==":"img-20170902-wa0031-800x599.jpg","BE4nCx2a+T2JhYKlbjNCpw==":"img-20170902-wa0026-1280x720.jpg","2bbTzkSkyZxgV3/w4ejnzw==":"img-20170902-wa0024-1280x720.jpg","SKo/0pZT7P5gN9VRQ4yNNQ==":"img-20170902-wa0025-1280x720.jpg","9WI96PMJV4EzGlCSWfesJA==":"img-20170902-wa0035-1152x864.jpg","wAwXOrcIFv7k8rGNTUJA4w==":"img-20170902-wa0036-1152x864.jpg","KFxWxOlS5ZidteyZnY/IpA==":"img-20170902-wa0045-1152x864.jpg","+1KdU7KfwcyI6th9fwKVDg==":"img-20170902-wa0040-1152x864.jpg","KdgTk4ONngCGikEyzvVauw==":"rolls_royce_wraith_white_rear_view_104125_1920x1080-1920x1080.jpg","vEpeun7R5MFfR7de1GbNkw==":"mbr-752x1080.jpg"}